MANIFEST.in
README.md
pyproject.toml
setup.py
amuse_distributed.egg-info/PKG-INFO
amuse_distributed.egg-info/SOURCES.txt
amuse_distributed.egg-info/dependency_links.txt
amuse_distributed.egg-info/requires.txt
amuse_distributed.egg-info/top_level.txt
src/amuse/community/distributed/Code.java
src/amuse/community/distributed/Makefile
src/amuse/community/distributed/Makefile.code
src/amuse/community/distributed/__init__.py
src/amuse/community/distributed/_version.py
src/amuse/community/distributed/distributed_datamodel.py
src/amuse/community/distributed/interface.py
src/amuse/community/distributed/known_issues.txt
src/amuse/community/distributed/logback.xml
src/amuse/community/distributed/smartsockets.properties
src/amuse/community/distributed/src/LICENSE
src/amuse/community/distributed/src/Makefile
src/amuse/community/distributed/src/NOTICE
src/amuse/community/distributed/src/README.md
src/amuse/community/distributed/src/build.xml
src/amuse/community/distributed/src/logback.xml
src/amuse/community/distributed/src/lib/ipl/TGGraphLayout-ibis-1.58.jar
src/amuse/community/distributed/src/lib/ipl/antenna-bin-1.0.0.jar
src/amuse/community/distributed/src/lib/ipl/asm-all-4.0.jar
src/amuse/community/distributed/src/lib/ipl/bcel-5.3-SNAPSHOT-1000411.jar
src/amuse/community/distributed/src/lib/ipl/commons-jxpath-1.1.jar
src/amuse/community/distributed/src/lib/ipl/commons-logging-api.jar
src/amuse/community/distributed/src/lib/ipl/commons-logging.jar
src/amuse/community/distributed/src/lib/ipl/ibis-compile-2.3.jar
src/amuse/community/distributed/src/lib/ipl/ibis-io-2.3.jar
src/amuse/community/distributed/src/lib/ipl/ibis-util-2.3.jar
src/amuse/community/distributed/src/lib/ipl/ipl-2.3.jar
src/amuse/community/distributed/src/lib/ipl/ipl-impl-2.3.jar
src/amuse/community/distributed/src/lib/ipl/ipl-impl-dummy-2.3.jar
src/amuse/community/distributed/src/lib/ipl/ipl-impl-lrmc-2.3.jar
src/amuse/community/distributed/src/lib/ipl/ipl-impl-multi-2.3.jar
src/amuse/community/distributed/src/lib/ipl/ipl-impl-nio-2.3.jar
src/amuse/community/distributed/src/lib/ipl/ipl-impl-smartsockets-2.3.jar
src/amuse/community/distributed/src/lib/ipl/ipl-impl-tcp-2.3.jar
